MANIFEST.in
setup.py
minsci/__init__.py
minsci/__main__.py
minsci/exceptions.py
minsci/helpers.py
minsci/my_requests.py
minsci.egg-info/PKG-INFO
minsci.egg-info/SOURCES.txt
minsci.egg-info/dependency_links.txt
minsci.egg-info/entry_points.txt
minsci.egg-info/not-zip-safe
minsci.egg-info/requires.txt
minsci.egg-info/top_level.txt
minsci/geotaxa/__init__.py
minsci/geotaxa/geotaxa.py
minsci/geotaxa/files/elements.txt
minsci/geotaxa/files/xmldata.p
minsci/mosaic/__init__.py
minsci/mosaic/mosaic.py
minsci/mosaic/offset.py
minsci/mosaic/organizer.py
minsci/mosaic/selector.py
minsci/mosaic/files/LICENSE.txt
minsci/mosaic/files/OpenSans-Regular.ttf
minsci/mosaic/files/image_types.txt
minsci/xmu/__init__.py
minsci/xmu/xmu.py