Metadata-Version: 1.1
Name: minsci
Version: 0.1.6
Summary: Tools for data management in Mineral Sciences at NMNH
Home-page: https://github.com/adamancer/minsci.git
Author: adamancer
Author-email: mansura@si.edu
License: MIT
Platform: UNKNOWN
Classifier: License :: OSI Approved :: MIT License
Classifier: Programming Language :: Python :: 2.7
